stutterbuddy/__init__.py
stutterbuddy/lib/Asset.py
stutterbuddy/lib/Job.py
stutterbuddy/lib/Stutterbuddy.py
stutterbuddy/lib/SubmissionSettings.py
stutterbuddy/lib/__init__.py
stutterbuddy-0.2.2.dist-info/LICENSE
stutterbuddy-0.2.2.dist-info/METADATA
stutterbuddy-0.2.2.dist-info/WHEEL
stutterbuddy-0.2.2.dist-info/top_level.txt
stutterbuddy-0.2.2.dist-info/RECORD
