Metadata-Version: 2.1
Name: stutterbuddy
Version: 0.2.2
Summary: Automate video editing with Stutterbuddy
Home-page: https://stutterbuddy.ch
Author: Jonas Briguet
Author-email: briguetjo@yahoo.de
Project-URL: Homepage, https://stutterbuddy.ch
Keywords: stutterbuddy video editing automation auto-editor ai machine-learning
Classifier: Programming Language :: Python :: 3
Classifier: License :: OSI Approved :: MIT License
Classifier: Operating System :: OS Independent
Requires-Python: >=3.7
License-File: LICENSE
Requires-Dist: requests
Requires-Dist: requests-toolbelt
Requires-Dist: urllib3
Requires-Dist: dict2xml
